<?xml version="1.0" encoding="UTF-8"?>

<brand xmlns="http://www.w3.org/1999/xhtml">
   
   <links>
      <link rel="stylesheet" href="css/default/results.css" type="text/css"/>
      <link rel="shortcut icon" href="icons/default/favicon.ico" />
   </links>
   
   <dynaxml.links>
      <link rel="stylesheet" href="css/default/content.css" type="text/css"/>
      <link rel="shortcut icon" href="icons/default/bandeau2.jpg" />


   </dynaxml.links>
   
   <header>
      <div class="header">
         <img src="icons/default/bandeau2.jpg" width="100%" alt="TMG -Thesaurus Musicarum Germanicorum" class="xtf-logo"/>
         <br class="clear" />
      </div>
   </header>
   
   <dynaxml.header>
      <div class="header">
       <img src="icons/default/bandeau2.jpg" width="100%" alt="TMG -Thesaurus Musicarum Germanicorum" class="xtf-logo"/>
         <br class="clear" />
      </div>
   </dynaxml.header>
   
   <footer>
      <div class="footer">
         <a href="mailto:christophe.guillotel@gmail.fr">Comments? Questions?</a> | <a href="javascript://" onclick="javascript:window.open('/xtf/search?smode=getLang','popup','width=500,height=200,resizable=no,scrollbars=no')">Choose Language</a>
      </div>
   </footer>
   
</brand>
